xanfis/__init__.py
xanfis/helpers/__init__.py
xanfis/helpers/membership_family.py
xanfis/helpers/metric_util.py
xanfis/helpers/preprocessor.py
xanfis/helpers/scaler_util.py
xanfis/helpers/validator.py
xanfis/models/__init__.py
xanfis/models/base_anfis.py
xanfis/models/bio_anfis.py
xanfis/models/classic_anfis.py
xanfis/models/gd_anfis.py
xanfis-1.1.0.dist-info/licenses/LICENSE
xanfis-1.1.0.dist-info/METADATA
xanfis-1.1.0.dist-info/WHEEL
xanfis-1.1.0.dist-info/top_level.txt
xanfis-1.1.0.dist-info/RECORD
